fibonacci.sv
module fibonacci(input clk, clr, output [13:0]f);
	
  	reg [13:0] fn1, fn;
	
	parameter fib_max = 21;
		
	// com reset assincrono
	always @(posedge clk) begin
		if (clr == 1) begin
			fn <= 0;
			fn1 <= 1;
		end else begin
			if (fn1 <= fib_max) begin
				fn1 <= fn1 + fn;
				fn <= fn1;
			end else begin
				fn <= 0;
				fn1 <= 1;
			end
		end
	end
	assign f = fn;
	
endmodule

fibonacci_tb.sv
// Code your testbench here
// or browse Examples

module fibonacci_tb;

  // inputs of dut as reg
  reg clk_tb, clr_tb;

  // outputs of dut as wire
  wire [13:0]f_tb;

  fibonacci my_fib_dut (
    .clk(clk_tb),
    .clr(clr_tb),
	 .f(f_tb)
  );

  initial begin
    clk_tb = 0;
    clr_tb = 0;
    clk_tb = 0;
  end

  always
    #5 clk_tb = ~clk_tb;

  initial begin
    $dumpfile("fibonacci.vcd");
    $dumpvars;
  end

  initial begin
    //$display("\t clk_tb, \t clr_tb, \t f_tb");
    $monitor("\t %b, \t %b, \t %d", clk_tb, clr_tb, f_tb);
  end

  initial begin
    #100 $finish;
  end
  
  
endmodule

simulation/modelsim/fibonacci.vcd
$date
	Fri Oct  9 17:16:55 2020
$end
$version
	ModelSim Version 2020.1
$end
$timescale
	1ps
$end

$scope module fibonacci_tb $end
$var reg 1 ! clk_tb $end
$var reg 1 " clr_tb $end
$var wire 1 # f_tb [13] $end
$var wire 1 $ f_tb [12] $end
$var wire 1 % f_tb [11] $end
$var wire 1 & f_tb [10] $end
$var wire 1 ' f_tb [9] $end
$var wire 1 ( f_tb [8] $end
$var wire 1 ) f_tb [7] $end
$var wire 1 * f_tb [6] $end
$var wire 1 + f_tb [5] $end
$var wire 1 , f_tb [4] $end
$var wire 1 - f_tb [3] $end
$var wire 1 . f_tb [2] $end
$var wire 1 / f_tb [1] $end
$var wire 1 0 f_tb [0] $end

$scope module my_fib_dut $end
$var parameter 32 1 fib_max $end
$var wire 1 2 clk $end
$var wire 1 3 clr $end
$var wire 1 # f [13] $end
$var wire 1 $ f [12] $end
$var wire 1 % f [11] $end
$var wire 1 & f [10] $end
$var wire 1 ' f [9] $end
$var wire 1 ( f [8] $end
$var wire 1 ) f [7] $end
$var wire 1 * f [6] $end
$var wire 1 + f [5] $end
$var wire 1 , f [4] $end
$var wire 1 - f [3] $end
$var wire 1 . f [2] $end
$var wire 1 / f [1] $end
$var wire 1 0 f [0] $end
$var reg 14 4 fn1 [13:0] $end
$var reg 14 5 fn [13:0] $end
$upscope $end
$upscope $end

$scope begin std $end
$upscope $end
$enddefinitions $end
#0
$dumpvars
0!
0"
bx 4
bx 5
b10101 1
x0
x/
x.
x-
x,
x+
x*
x)
x(
x'
x&
x%
x$
x#
02
03
$end
#5
1!
12
b0 5
b1 4
00
0/
0.
0-
0,
0+
0*
0)
0(
0'
0&
0%
0$
0#
#10
0!
02
#15
1!
12
b1 5
10
#20
0!
02
#25
1!
12
b10 4
#30
0!
02
#35
1!
12
b11 4
b10 5
00
1/
#40
0!
02
#45
1!
12
b101 4
b11 5
10
#50
0!
02
#55
1!
12
b1000 4
b101 5
0/
1.
#60
0!
02
#65
1!
12
b1101 4
b1000 5
00
0.
1-
#70
0!
02
#75
1!
12
b10101 4
b1101 5
10
1.
#80
0!
02
#85
1!
12
b100010 4
b10101 5
0-
1,
#90
0!
02
#95
1!
12
b0 5
b1 4
00
0.
0,
